hud/__init__.py
hud/__main__.py
hud/settings.py
hud/types.py
hud/version.py
hud/agents/__init__.py
hud/agents/base.py
hud/agents/claude.py
hud/agents/gateway.py
hud/agents/gemini.py
hud/agents/gemini_cua.py
hud/agents/grounded_openai.py
hud/agents/openai.py
hud/agents/openai_chat.py
hud/agents/operator.py
hud/agents/resolver.py
hud/agents/types.py
hud/agents/misc/__init__.py
hud/agents/misc/integration_test_agent.py
hud/agents/misc/response_agent.py
hud/agents/tests/__init__.py
hud/agents/tests/conftest.py
hud/agents/tests/test_base.py
hud/agents/tests/test_base_runtime.py
hud/agents/tests/test_claude.py
hud/agents/tests/test_gemini.py
hud/agents/tests/test_grounded_openai_agent.py
hud/agents/tests/test_openai.py
hud/agents/tests/test_operator.py
hud/agents/tests/test_resolver.py
hud/agents/tests/test_run_eval.py
hud/cli/__init__.py
hud/cli/__main__.py
hud/cli/analyze.py
hud/cli/build.py
hud/cli/clone.py
hud/cli/debug.py
hud/cli/deploy.py
hud/cli/dev.py
hud/cli/eval.py
hud/cli/get.py
hud/cli/init.py
hud/cli/link.py
hud/cli/list_func.py
hud/cli/pull.py
hud/cli/push.py
hud/cli/remove.py
hud/cli/rft.py
hud/cli/rft_status.py
hud/cli/flows/__init__.py
hud/cli/flows/dev.py
hud/cli/flows/init.py
hud/cli/flows/tasks.py
hud/cli/flows/templates.py
hud/cli/flows/tests/__init__.py
hud/cli/flows/tests/test_dev.py
hud/cli/tests/__init__.py
hud/cli/tests/test_analyze.py
hud/cli/tests/test_analyze_metadata.py
hud/cli/tests/test_analyze_module.py
hud/cli/tests/test_build.py
hud/cli/tests/test_build_failure.py
hud/cli/tests/test_build_module.py
hud/cli/tests/test_cli_init.py
hud/cli/tests/test_cli_main.py
hud/cli/tests/test_cli_more_wrappers.py
hud/cli/tests/test_cli_root.py
hud/cli/tests/test_clone.py
hud/cli/tests/test_convert.py
hud/cli/tests/test_cursor.py
hud/cli/tests/test_debug.py
hud/cli/tests/test_debug_directory_mode.py
hud/cli/tests/test_deploy.py
hud/cli/tests/test_dev.py
hud/cli/tests/test_eval.py
hud/cli/tests/test_eval_bedrock.py
hud/cli/tests/test_init.py
hud_python-0.5.17.dist-info/METADATA
hud_python-0.5.17.dist-info/WHEEL
hud_python-0.5.17.dist-info/entry_points.txt
hud_python-0.5.17.dist-info/licenses/LICENSE
hud_python-0.5.17.dist-info/RECORD
