Metadata-Version: 2.4
Name: hud-python
Version: 0.5.17
Summary: SDK for the HUD platform.
Project-URL: Homepage, https://github.com/hud-evals/hud-python
Project-URL: Bug Tracker, https://github.com/hud-evals/hud-python/issues
Project-URL: Documentation, https://docs.hud.ai
Author-email: HUD <founders@hud.ai>
License: MIT License
License-File: LICENSE
Classifier: Development Status :: 4 - Beta
Classifier: Intended Audience :: Developers
Classifier: Programming Language :: Python :: 3
Classifier: Programming Language :: Python :: 3.11
Classifier: Programming Language :: Python :: 3.12
Classifier: Programming Language :: Python :: 3.13
Requires-Python: <3.13,>=3.11
Requires-Dist: blessed>=1.20.0
Requires-Dist: fastmcp==2.13.3
Requires-Dist: httpx<1,>=0.23.0
Requires-Dist: mcp<1.23,>1.21.1
Requires-Dist: openai>=2.8.1
Requires-Dist: packaging>=21.0
Requires-Dist: prompt-toolkit==3.0.51
Requires-Dist: pydantic-settings<3,>=2.2
Requires-Dist: pydantic<3,>=2.6
Requires-Dist: questionary==2.1.0
Requires-Dist: rich>=13.0.0
Requires-Dist: scarf-sdk>=0.1.0
Requires-Dist: toml>=0.10.2
Requires-Dist: typer>=0.9.0
Requires-Dist: watchfiles>=0.21.0
Provides-Extra: agent
Requires-Dist: anthropic>=0.75; extra == 'agent'
Requires-Dist: datasets>=2.14.0; extra == 'agent'
Requires-Dist: google-genai; extra == 'agent'
Requires-Dist: langchain>=1.1.0; extra == 'agent'
Requires-Dist: mcp-use==1.5.0; extra == 'agent'
Requires-Dist: openai-agents; extra == 'agent'
Requires-Dist: pillow>=11.1.0; extra == 'agent'
Requires-Dist: tornado>=6.5.2; extra == 'agent'
Provides-Extra: agents
Requires-Dist: anthropic>=0.75; extra == 'agents'
Requires-Dist: datasets>=2.14.0; extra == 'agents'
Requires-Dist: google-genai; extra == 'agents'
Requires-Dist: langchain>=1.1.0; extra == 'agents'
Requires-Dist: mcp-use==1.5.0; extra == 'agents'
Requires-Dist: openai-agents; extra == 'agents'
Requires-Dist: pillow>=11.1.0; extra == 'agents'
Requires-Dist: tornado>=6.5.2; extra == 'agents'
Provides-Extra: bedrock
Requires-Dist: anthropic[bedrock]>=0.75; extra == 'bedrock'
Provides-Extra: dev
Requires-Dist: anthropic>=0.75; extra == 'dev'
Requires-Dist: datasets>=2.14.0; extra == 'dev'
Requires-Dist: dotenv>=0.9.9; extra == 'dev'
Requires-Dist: google-adk; extra == 'dev'
Requires-Dist: google-genai; extra == 'dev'
Requires-Dist: ipykernel; extra == 'dev'
Requires-Dist: ipython<9; extra == 'dev'
Requires-Dist: jupyter-client; extra == 'dev'
Requires-Dist: jupyter-core; extra == 'dev'
Requires-Dist: langchain>=1.1.0; extra == 'dev'
Requires-Dist: llama-index-core; extra == 'dev'
Requires-Dist: mcp-use==1.5.0; extra == 'dev'
Requires-Dist: openai-agents; extra == 'dev'
Requires-Dist: pillow>=11.1.0; extra == 'dev'
Requires-Dist: playwright; extra == 'dev'
Requires-Dist: pyautogui>=0.9.54; extra == 'dev'
Requires-Dist: pyright==1.1.407; extra == 'dev'
Requires-Dist: pytest-asyncio; extra == 'dev'
Requires-Dist: pytest-cov; extra == 'dev'
Requires-Dist: pytest-mock; extra == 'dev'
Requires-Dist: pytest>=8.1.1; extra == 'dev'
Requires-Dist: ruff>=0.11.8; extra == 'dev'
Requires-Dist: tornado>=6.5.2; extra == 'dev'
